atoolbox/__init__.py
atoolbox/__main__.py
atoolbox/auth.py
atoolbox/class_views.py
atoolbox/cli.py
atoolbox/create_app.py
atoolbox/exceptions.py
atoolbox/json_tools.py
atoolbox/logs.py
atoolbox/middleware.py
atoolbox/network.py
atoolbox/patch_methods.py
atoolbox/settings.py
atoolbox/test_utils.py
atoolbox/utils.py
atoolbox/version.py
atoolbox/views.py
atoolbox/bread/__init__.py
atoolbox/bread/main.py
atoolbox/db/__init__.py
atoolbox/db/connection.py
atoolbox/db/helpers.py
atoolbox/db/redis.py
aiohttp_toolbox-0.6.3.dist-info/LICENSE
aiohttp_toolbox-0.6.3.dist-info/METADATA
aiohttp_toolbox-0.6.3.dist-info/WHEEL
aiohttp_toolbox-0.6.3.dist-info/entry_points.txt
aiohttp_toolbox-0.6.3.dist-info/top_level.txt
aiohttp_toolbox-0.6.3.dist-info/zip-safe
aiohttp_toolbox-0.6.3.dist-info/RECORD
