Metadata-Version: 2.1
Name: aiohttp-toolbox
Version: 0.6.3
Summary: Tools for aiohttp I want to reuse.
Home-page: https://github.com/samuelcolvin/aiohttp-tools
Author: Samuel Colvin
Author-email: s@muelcolvin.com
License: MIT
Platform: UNKNOWN
Classifier: Development Status :: 4 - Beta
Classifier: Programming Language :: Python
Classifier: Programming Language :: Python :: 3
Classifier: Programming Language :: Python :: 3 :: Only
Classifier: Programming Language :: Python :: 3.7
Classifier: Intended Audience :: Developers
Classifier: Intended Audience :: Information Technology
Classifier: Intended Audience :: System Administrators
Classifier: License :: OSI Approved :: MIT License
Classifier: Operating System :: Unix
Classifier: Operating System :: POSIX :: Linux
Classifier: Environment :: MacOS X
Classifier: Topic :: Internet
Requires-Python: >=3.7
Requires-Dist: aiodns (>=2.0.0)
Requires-Dist: aiohttp (>=3.5.4)
Requires-Dist: async-timeout (>=3.0.1)
Requires-Dist: cchardet (>=2.1.4)
Requires-Dist: pydantic (>=1)
Requires-Dist: sentry-sdk (>=0.11.1)
Requires-Dist: uvloop (>=0.11.2)
Requires-Dist: dataclasses (>=0.6) ; python_version < "3.7"
Provides-Extra: all
Requires-Dist: aiohttp-session (>=2.7.0) ; extra == 'all'
Requires-Dist: arq (>=0.16) ; extra == 'all'
Requires-Dist: asyncpg (>=0.17.0) ; extra == 'all'
Requires-Dist: buildpg (>=0.2.1) ; extra == 'all'
Requires-Dist: cryptography (>=2.4.1) ; extra == 'all'
Requires-Dist: ipython (>=7.7.0) ; extra == 'all'
